{
 "items": [
  {
   "url": "https://dirtydoglinks.com/402949998.html",
   "quality": "best",
   "time": "2026-04-29T08:44:40.009Z"
  },
  {
   "url": "https://dirtydoglinks.com/402949998.html",
   "quality": "best",
   "time": "2026-04-29T08:45:04.003Z"
  },
  {
   "url": "https://dirtydoglinks.com/402949998.html",
   "quality": "best",
   "time": "2026-04-29T08:45:11.757Z"
  },
  {
   "url": "https://he.xhamster.com/categories/pet-play",
   "quality": "best",
   "time": "2026-04-29T08:45:16.094Z"
  },
  {
   "url": "http://www.xxxbule.com/he/sex-clips/ladies-intercourse-with-animals/",
   "quality": "best",
   "time": "2026-04-29T08:45:17.099Z"
  }
 ]
}