{"query": "ראיון עם חטוף שוחרר", "type": "video", "count": 100, "results": [{"title": "שוחרר מהשבי וגילה שזוגתו שרדה את הטבח: אלי-ה כהן חזר הביתה", "url": "https://www.youtube.com/watch?v=qTv77Fzrnsw", "thumb": "https://i.ytimg.com/vi/qTv77Fzrnsw/hq720.jpg?sqp=-oaymwEcCNAFEJQDSFXyq4qpAw4IARUAAIhCGAFwAcABBg==&rs=AOn4CLCmdfW48pnK1RaFoZL5c9YVPXFOzw", "duration": 382.0, "channel": "כאן | חדשות - תאגיד השידור הישראלי", "source": "YouTube", "kind": "video", "formats": [{"label": "MP4 מלא", "value": "best", "format": "video"}, {"label": "MP4 1080p", "value": "1080", "format": "video"}, {"label": "MP4 720p", "value": "720", "format": "video"}, {"label": "MP4 480p", "value": "480", "format": "video"}, {"label": "MP3 שמע", "value": "best", "format": "audio"}], "description": "", "date": ""}, {"title": "העסקה עם חמאס, שחרור החטופים וגורל החות'ים | השר סמוטריץ' בראיון בפטריוטים", "url": "https://www.youtube.com/watch?v=4nQsbct7cWs", "thumb": "https://i.ytimg.com/vi/4nQsbct7cWs/hq720.jpg?sqp=-oaymwEcCNAFEJQDSFXyq4qpAw4IARUAAIhCGAFwAcABBg==&rs=AOn4CLAXQKK6jLn2Us6A5nP7YsqIMDGHnw", "duration": 944.0, "channel": "C14", "source": "YouTube", "kind": "video", "formats": [{"label": "MP4 מלא", "value": "best", "format": "video"}, {"label": "MP4 1080p", "value": "1080", "format": "video"}, {"label": "MP4 720p", "value": "720", "format": "video"}, {"label": "MP4 480p", "value": "480", "format": "video"}, {"label": "MP3 שמע", "value": "best", "format": "audio"}], "description": "", "date": ""}, {"title": "לוחמי הימ\"מ והשב\"כ מחלצים חטופים תחת אש כבדה משבי חמאס בעזה", "url": "https://www.youtube.com/watch?v=fhfWDu-hc34", "thumb": "https://i.ytimg.com/vi/fhfWDu-hc34/hq720.jpg?sqp=-oaymwEcCNAFEJQDSFXyq4qpAw4IARUAAIhCGAFwAcABBg==&rs=AOn4CLDGAMIl-l3EZ1GiqPq1XBCuXz4CNQ", "duration": 46.0, "channel": "Israel Police - משטרת ישראל", "source": "YouTube", "kind": "video", "formats": [{"label": "MP4 מלא", "value": "best", "format": "video"}, {"label": "MP4 1080p", "value": "1080", "format": "video"}, {"label": "MP4 720p", "value": "720", "format": "video"}, {"label": "MP4 480p", "value": "480", "format": "video"}, {"label": "MP3 שמע", "value": "best", "format": "audio"}], "description": "", "date": ""}, {"title": "אליה כהן ראיון מלא - \"אין יותר נאצי מזה\" החטוף ששוחרר מדבר לראשונה חדשות ערוץ 12 - Eliya Cohen", "url": "https://www.youtube.com/watch?v=I_yykR5DJK0", "thumb": "https://i.ytimg.com/vi/I_yykR5DJK0/hq720.jpg?sqp=-oaymwEcCNAFEJQDSFXyq4qpAw4IARUAAIhCGAFwAcABBg==&rs=AOn4CLCE8PVRw9YbbZuVq7Fd8CiU-xZpgg", "duration": 2595.0, "channel": "Miki Aminov", "source": "YouTube", "kind": "video", "formats": [{"label": "MP4 מלא", "value": "best", "format": "video"}, {"label": "MP4 1080p", "value": "1080", "format": "video"}, {"label": "MP4 720p", "value": "720", "format": "video"}, {"label": "MP4 480p", "value": "480", "format": "video"}, {"label": "MP3 שמע", "value": "best", "format": "audio"}], "description": "", "date": ""}, {"title": "אליה כהן פוגש את בת זוגו לאחר השחרור משבי חמאס", "url": "https://www.youtube.com/watch?v=Eg17MfxxIKc", "thumb": "https://i.ytimg.com/vi/Eg17MfxxIKc/hqdefault.jpg?sqp=-oaymwE2COADEI4CSFXyq4qpAygIARUAAIhCGAFwAcABBvABAfgB3gOAAoACigIMCAAQARhlIEsoPTAP&rs=AOn4CLC03V7TYlCWeeLB8VVHR_LFOhJ48w", "duration": 23.0, "channel": "חדשות 24", "source": "YouTube", "kind": "video", "formats": [{"label": "MP4 מלא", "value": "best", "format": "video"}, {"label": "MP4 1080p", "value": "1080", "format": "video"}, {"label": "MP4 720p", "value": "720", "format": "video"}, {"label": "MP4 480p", "value": "480", "format": "video"}, {"label": "MP3 שמע", "value": "best", "format": "audio"}], "description": "", "date": ""}, {"title": "הילדים שחזרו מהשבי מדברים: \"נועם נסגר בחדר לבד, אמילי הוכרחה לדבר בשקט\"", "url": "https://www.youtube.com/watch?v=BYeQjD49Rso", "thumb": "https://i.ytimg.com/vi/BYeQjD49Rso/hq720.jpg?sqp=-oaymwE2CNAFEJQDSFXyq4qpAygIARUAAIhCGAFwAcABBvABAfgB_gmAAtAFigIMCAAQARhyIFQoQTAP&rs=AOn4CLBH29aLvb4aouuorHuTTS-1AXtufQ", "duration": 367.0, "channel": "חדשות 13", "source": "YouTube", "kind": "video", "formats": [{"label": "MP4 מלא", "value": "best", "format": "video"}, {"label": "MP4 1080p", "value": "1080", "format": "video"}, {"label": "MP4 720p", "value": "720", "format": "video"}, {"label": "MP4 480p", "value": "480", "format": "video"}, {"label": "MP3 שמע", "value": "best", "format": "audio"}], "description": "", "date": ""}, {"title": "סוף סוף בבית: אחרי שנתיים בגיהינום - היום הראשון של החטופים כאנשים חופשיים", "url": "https://www.youtube.com/watch?v=P7myPjWgDHA", "thumb": "https://i.ytimg.com/vi/P7myPjWgDHA/hq720.jpg?sqp=-oaymwEcCNAFEJQDSFXyq4qpAw4IARUAAIhCGAFwAcABBg==&rs=AOn4CLD24QjzzQmlS5X9TxE7YY5PQFRU5Q", "duration": 285.0, "channel": "כאן | חדשות - תאגיד השידור הישראלי", "source": "YouTube", "kind": "video", "formats": [{"label": "MP4 מלא", "value": "best", "format": "video"}, {"label": "MP4 1080p", "value": "1080", "format": "video"}, {"label": "MP4 720p", "value": "720", "format": "video"}, {"label": "MP4 480p", "value": "480", "format": "video"}, {"label": "MP3 שמע", "value": "best", "format": "audio"}], "description": "", "date": ""}, {"title": "זעזוע בעולם: החטופות ששוחררו חושפות מה עברו בשבי חמאס", "url": "https://www.youtube.com/watch?v=xzQZt4fyqXw", "thumb": "https://i.ytimg.com/vi/xzQZt4fyqXw/hq720.jpg?sqp=-oaymwEcCNAFEJQDSFXyq4qpAw4IARUAAIhCGAFwAcABBg==&rs=AOn4CLDtltTLHyTh8JpklUXiFPx-o4hrgQ", "duration": 180.0, "channel": "כאן | חדשות - תאגיד השידור הישראלי", "source": "YouTube", "kind": "video", "formats": [{"label": "MP4 מלא", "value": "best", "format": "video"}, {"label": "MP4 1080p", "value": "1080", "format": "video"}, {"label": "MP4 720p", "value": "720", "format": "video"}, {"label": "MP4 480p", "value": "480", "format": "video"}, {"label": "MP3 שמע", "value": "best", "format": "audio"}], "description": "", "date": ""}, {"title": "האהבה שניצחה הכול: האיחוד המרגש של אריאל קוניו וארבל יהוד", "url": "https://www.youtube.com/watch?v=dAL1TxKplgY", "thumb": "https://i.ytimg.com/vi/dAL1TxKplgY/hq720.jpg?sqp=-oaymwEcCNAFEJQDSFXyq4qpAw4IARUAAIhCGAFwAcABBg==&rs=AOn4CLAsqmX5zp-obfK81yasuNkJHEbZVA", "duration": 217.0, "channel": "כאן | חדשות - תאגיד השידור הישראלי", "source": "YouTube", "kind": "video", "formats": [{"label": "MP4 מלא", "value": "best", "format": "video"}, {"label": "MP4 1080p", "value": "1080", "format": "video"}, {"label": "MP4 720p", "value": "720", "format": "video"}, {"label": "MP4 480p", "value": "480", "format": "video"}, {"label": "MP3 שמע", "value": "best", "format": "audio"}], "description": "", "date": ""}, {"title": "\"הוא נישק אותה וכיוון אקדח לראשה\": עדויות מטלטלות משבי חמאס", "url": "https://www.youtube.com/watch?v=WmFoV7UIKDA", "thumb": "https://i.ytimg.com/vi/WmFoV7UIKDA/hq720.jpg?sqp=-oaymwEcCNAFEJQDSFXyq4qpAw4IARUAAIhCGAFwAcABBg==&rs=AOn4CLCxK85nXw3EE6wV2Xo02aF18hNshQ", "duration": 199.0, "channel": "כאן | חדשות - תאגיד השידור הישראלי", "source": "YouTube", "kind": "video", "formats": [{"label": "MP4 מלא", "value": "best", "format": "video"}, {"label": "MP4 1080p", "value": "1080", "format": "video"}, {"label": "MP4 720p", "value": "720", "format": "video"}, {"label": "MP4 480p", "value": "480", "format": "video"}, {"label": "MP3 שמע", "value": "best", "format": "audio"}], "description": "", "date": ""}, {"title": "חקירת שב\"כ בה מתאר מחבל חמאס מחמד אמג'ד מחמד אלח'לילי כיצד פעל בטבח בישובי העוטף ב-07.10.2023", "url": "https://www.youtube.com/watch?v=29gwMHlJsXY", "thumb": "https://i.ytimg.com/vi/29gwMHlJsXY/hq720.jpg?sqp=-oaymwE2CNAFEJQDSFXyq4qpAygIARUAAIhCGAFwAcABBvABAfgB_gmAAtAFigIMCAAQARhlIF0oTjAP&rs=AOn4CLDCg2avv-i6boUYyYZabwunY4JLNQ", "duration": 1015.0, "channel": "שירות הביטחון הכללי- Israeli Security Agency", "source": "YouTube", "kind": "video", "formats": [{"label": "MP4 מלא", "value": "best", "format": "video"}, {"label": "MP4 1080p", "value": "1080", "format": "video"}, {"label": "MP4 720p", "value": "720", "format": "video"}, {"label": "MP4 480p", "value": "480", "format": "video"}, {"label": "MP3 שמע", "value": "best", "format": "audio"}], "description": "", "date": ""}, {"title": "עמוס מלכא. ראיון עם יואב לימור ונסלי ברדה. חדשות הבוקר ערוץ 12. 11/3/2025", "url": "https://www.youtube.com/watch?v=gcZmgBl8A88", "thumb": "https://i.ytimg.com/vi/gcZmgBl8A88/hqdefault.jpg?sqp=-oaymwEcCOADEI4CSFXyq4qpAw4IARUAAIhCGAFwAcABBg==&rs=AOn4CLDNhnx_yNH06lK7XbkgLV6-wKq7rA", "duration": 455.0, "channel": "Amos Malka", "source": "YouTube", "kind": "video", "formats": [{"label": "MP4 מלא", "value": "best", "format": "video"}, {"label": "MP4 1080p", "value": "1080", "format": "video"}, {"label": "MP4 720p", "value": "720", "format": "video"}, {"label": "MP4 480p", "value": "480", "format": "video"}, {"label": "MP3 שמע", "value": "best", "format": "audio"}], "description": "", "date": ""}, {"title": "הרבה תמר אלעד אפלבום בראיון לליאת רגב על שחרור חטופים בצל החזרתם של גופות חטופים", "url": "https://www.youtube.com/watch?v=uSI8faFzGXA", "thumb": "https://i.ytimg.com/vi/uSI8faFzGXA/hq720.jpg?sqp=-oaymwE2CNAFEJQDSFXyq4qpAygIARUAAIhCGAFwAcABBvABAfgB_gmAAtAFigIMCAAQARhlIFIoRTAP&rs=AOn4CLAC0DEH_59X6Dd2ZDImY2UTySFMfA", "duration": 355.0, "channel": "מכון שלום הרטמן", "source": "YouTube", "kind": "video", "formats": [{"label": "MP4 מלא", "value": "best", "format": "video"}, {"label": "MP4 1080p", "value": "1080", "format": "video"}, {"label": "MP4 720p", "value": "720", "format": "video"}, {"label": "MP4 480p", "value": "480", "format": "video"}, {"label": "MP3 שמע", "value": "best", "format": "audio"}], "description": "", "date": ""}, {"title": "רן גואילי הוא החטוף האחרון בעזה: \"הראשון לצאת - האחרון לשוב\"", "url": "https://www.youtube.com/watch?v=yKrlhdzc1hI", "thumb": "https://i.ytimg.com/vi/yKrlhdzc1hI/hq720.jpg?sqp=-oaymwEcCNAFEJQDSFXyq4qpAw4IARUAAIhCGAFwAcABBg==&rs=AOn4CLD7KWadB_WX4NgIN9CB_ovijyqdsA", "duration": 227.0, "channel": "כאן | חדשות - תאגיד השידור הישראלי", "source": "YouTube", "kind": "video", "formats": [{"label": "MP4 מלא", "value": "best", "format": "video"}, {"label": "MP4 1080p", "value": "1080", "format": "video"}, {"label": "MP4 720p", "value": "720", "format": "video"}, {"label": "MP4 480p", "value": "480", "format": "video"}, {"label": "MP3 שמע", "value": "best", "format": "audio"}], "description": "", "date": ""}, {"title": "החטוף שגב כלפון שוחרר לביתו - הרב דוד שלום נקי", "url": "https://www.youtube.com/watch?v=MKTeCTe4Zkw", "thumb": "https://i.ytimg.com/vi/MKTeCTe4Zkw/hq720.jpg?sqp=-oaymwE2CNAFEJQDSFXyq4qpAygIARUAAIhCGAFwAcABBvABAfgB3AOAAtIGigIMCAAQARhKIFUoZTAP&rs=AOn4CLDw4-1O-_WjgN7wyez1cfEuyaWNtw", "duration": 392.0, "channel": "הרב דוד שלום נקי שליט״א - הערוץ הרשמי", "source": "YouTube", "kind": "video", "formats": [{"label": "MP4 מלא", "value": "best", "format": "video"}, {"label": "MP4 1080p", "value": "1080", "format": "video"}, {"label": "MP4 720p", "value": "720", "format": "video"}, {"label": "MP4 480p", "value": "480", "format": "video"}, {"label": "MP3 שמע", "value": "best", "format": "audio"}], "description": "", "date": ""}, {"title": "שליח טראמפ - אדם בוהלר מדבר: \"ניתן להגיע לפעימת שחרור נוספת\"", "url": "https://www.youtube.com/watch?v=xRH3CYeAMfE", "thumb": "https://i.ytimg.com/vi/xRH3CYeAMfE/hq720.jpg?sqp=-oaymwE2CNAFEJQDSFXyq4qpAygIARUAAIhCGAFwAcABBvABAfgB_gmAAtAFigIMCAAQARg1IEEofzAP&rs=AOn4CLAyfvrQq2Au2vYZszZwJtMfn_zZCQ", "duration": 214.0, "channel": "i24NEWS עברית", "source": "YouTube", "kind": "video", "formats": [{"label": "MP4 מלא", "value": "best", "format": "video"}, {"label": "MP4 1080p", "value": "1080", "format": "video"}, {"label": "MP4 720p", "value": "720", "format": "video"}, {"label": "MP4 480p", "value": "480", "format": "video"}, {"label": "MP3 שמע", "value": "best", "format": "audio"}], "description": "", "date": ""}, {"title": "חזרו לרקוד את החיים: אחרי שנתיים קשות בשבי - חטופי הנובה שבו לישראל", "url": "https://www.youtube.com/watch?v=lsEDKOA7Ln0", "thumb": "https://i.ytimg.com/vi/lsEDKOA7Ln0/hq720.jpg?sqp=-oaymwEcCNAFEJQDSFXyq4qpAw4IARUAAIhCGAFwAcABBg==&rs=AOn4CLBcAJ1_ib7ag6DaWKpCtVHxBIPrMw", "duration": 413.0, "channel": "כאן | חדשות - תאגיד השידור הישראלי", "source": "YouTube", "kind": "video", "formats": [{"label": "MP4 מלא", "value": "best", "format": "video"}, {"label": "MP4 1080p", "value": "1080", "format": "video"}, {"label": "MP4 720p", "value": "720", "format": "video"}, {"label": "MP4 480p", "value": "480", "format": "video"}, {"label": "MP3 שמע", "value": "best", "format": "audio"}], "description": "", "date": ""}, {"title": "ראש חטיבת המחקר באמ\"ן על שחרור 4 החטופים: \"ניתן וצריך למנף זאת בתזמון הנוכחי\"", "url": "https://www.youtube.com/watch?v=10atlIfx1Yc", "thumb": "https://i.ytimg.com/vi/10atlIfx1Yc/hqdefault.jpg?sqp=-oaymwE2COADEI4CSFXyq4qpAygIARUAAIhCGAFwAcABBvABAfgB1AaAAuADigIMCAAQARhVIFUoZTAP&rs=AOn4CLCQvwD5cM_7QMYEhGSl3U0LJk9Zgg", "duration": 336.0, "channel": "Jerusalem Center for Security and Foreign Affairs", "source": "YouTube", "kind": "video", "formats": [{"label": "MP4 מלא", "value": "best", "format": "video"}, {"label": "MP4 1080p", "value": "1080", "format": "video"}, {"label": "MP4 720p", "value": "720", "format": "video"}, {"label": "MP4 480p", "value": "480", "format": "video"}, {"label": "MP3 שמע", "value": "best", "format": "audio"}], "description": "", "date": ""}, {"title": "Amit Segal Interviews Released Hostage Yosef-Haim Ohana", "url": "https://www.youtube.com/watch?v=c_AChRn8Zlg", "thumb": "https://i.ytimg.com/vi/c_AChRn8Zlg/hq720.jpg?sqp=-oaymwE2CNAFEJQDSFXyq4qpAygIARUAAIhCGAFwAcABBvABAfgB_gmAAtAFigIMCAAQARhyIE8oOTAP&rs=AOn4CLBslVW0eZkPLY3cOD3EyG6_9ZNEQg", "duration": 1930.0, "channel": "Amit Segal עמית סגל", "source": "YouTube", "kind": "video", "formats": [{"label": "MP4 מלא", "value": "best", "format": "video"}, {"label": "MP4 1080p", "value": "1080", "format": "video"}, {"label": "MP4 720p", "value": "720", "format": "video"}, {"label": "MP4 480p", "value": "480", "format": "video"}, {"label": "MP3 שמע", "value": "best", "format": "audio"}], "description": "", "date": ""}, {"title": "בת החטוף מבולבלת ולחוצה: איך למוטט חמאס הולך עם שחרור חטופים. איילה חסון מסבירה לה איך זה מסתדר", "url": "https://www.youtube.com/watch?v=wUfYVOdWfbE", "thumb": "https://i.ytimg.com/vi/wUfYVOdWfbE/hqdefault.jpg?sqp=-oaymwEcCOADEI4CSFXyq4qpAw4IARUAAIhCGAFwAcABBg==&rs=AOn4CLDAOM1BYsOMdkIRNPtjOBtFVugzTQ", "duration": 520.0, "channel": "John Smith", "source": "YouTube", "kind": "video", "formats": [{"label": "MP4 מלא", "value": "best", "format": "video"}, {"label": "MP4 1080p", "value": "1080", "format": "video"}, {"label": "MP4 720p", "value": "720", "format": "video"}, {"label": "MP4 480p", "value": "480", "format": "video"}, {"label": "MP3 שמע", "value": "best", "format": "audio"}], "description": "", "date": ""}, {"title": "חדשות השבוע 13.07.18: שחרור הילד החטוף  | המהדורה המלאה", "url": "https://www.youtube.com/watch?v=mC3BB7TYNYA", "thumb": "https://i.ytimg.com/vi/mC3BB7TYNYA/hq720.jpg?sqp=-oaymwEcCNAFEJQDSFXyq4qpAw4IARUAAIhCGAFwAcABBg==&rs=AOn4CLDZ3bj0oRp03_BwlWOwYP_M94bxHA", "duration": 5953.0, "channel": "כאן | חדשות - תאגיד השידור הישראלי", "source": "YouTube", "kind": "video", "formats": [{"label": "MP4 מלא", "value": "best", "format": "video"}, {"label": "MP4 1080p", "value": "1080", "format": "video"}, {"label": "MP4 720p", "value": "720", "format": "video"}, {"label": "MP4 480p", "value": "480", "format": "video"}, {"label": "MP3 שמע", "value": "best", "format": "audio"}], "description": "", "date": ""}, {"title": "\"ראיתי את אלוהים\": השורדים מדברים על האמונה שהתחזקה | אלוהים ישמור - פרק 1", "url": "https://www.youtube.com/watch?v=DL8UQgFx8y0", "thumb": "https://i.ytimg.com/vi/DL8UQgFx8y0/hq720.jpg?sqp=-oaymwEcCNAFEJQDSFXyq4qpAw4IARUAAIhCGAFwAcABBg==&rs=AOn4CLCPa5o86OmdoXEZhqpj5Jypfc0ALw", "duration": 953.0, "channel": "כאן | חדשות - תאגיד השידור הישראלי", "source": "YouTube", "kind": "video", "formats": [{"label": "MP4 מלא", "value": "best", "format": "video"}, {"label": "MP4 1080p", "value": "1080", "format": "video"}, {"label": "MP4 720p", "value": "720", "format": "video"}, {"label": "MP4 480p", "value": "480", "format": "video"}, {"label": "MP3 שמע", "value": "best", "format": "audio"}], "description": "", "date": ""}, {"title": "\"חזרתי מפגישה עם השטן\": רום ברסלבסקי חושף את הפגיעות המיניות בשבי", "url": "https://www.youtube.com/watch?v=fwl63TeL_pM", "thumb": "https://i.ytimg.com/vi/fwl63TeL_pM/hq720.jpg?sqp=-oaymwEcCNAFEJQDSFXyq4qpAw4IARUAAIhCGAFwAcABBg==&rs=AOn4CLCTvYh8z6Fk0eFzlFJxgy0x4RLgzw", "duration": 158.0, "channel": "חדשות 13 and רשת 13", "source": "YouTube", "kind": "video", "formats": [{"label": "MP4 מלא", "value": "best", "format": "video"}, {"label": "MP4 1080p", "value": "1080", "format": "video"}, {"label": "MP4 720p", "value": "720", "format": "video"}, {"label": "MP4 480p", "value": "480", "format": "video"}, {"label": "MP3 שמע", "value": "best", "format": "audio"}], "description": "", "date": ""}, {"title": "התאומים התאחדו אחרי שנתיים בנפרד, עמרי חזר לבנות: חטופי העוטף שבו הביתה", "url": "https://www.youtube.com/watch?v=3_5tISh2r7Q", "thumb": "https://i.ytimg.com/vi/3_5tISh2r7Q/hq720.jpg?sqp=-oaymwEcCNAFEJQDSFXyq4qpAw4IARUAAIhCGAFwAcABBg==&rs=AOn4CLBicJJ-Oc6_IfWMbTOPnd1B-YeuVg", "duration": 326.0, "channel": "כאן | חדשות - תאגיד השידור הישראלי", "source": "YouTube", "kind": "video", "formats": [{"label": "MP4 מלא", "value": "best", "format": "video"}, {"label": "MP4 1080p", "value": "1080", "format": "video"}, {"label": "MP4 720p", "value": "720", "format": "video"}, {"label": "MP4 480p", "value": "480", "format": "video"}, {"label": "MP3 שמע", "value": "best", "format": "audio"}], "description": "", "date": ""}, {"title": "*כשמשחררים חטופים כולנו נושמים, כשמשחררים מחבלים אני עוצר נשימה.*ראיון לטלוויזיה הצרפתית, rtl", "url": "https://www.youtube.com/watch?v=-SkTTCb12Rg", "thumb": "https://i.ytimg.com/vi/-SkTTCb12Rg/hqdefault.jpg?sqp=-oaymwE2COADEI4CSFXyq4qpAygIARUAAIhCGAFwAcABBvABAfgB_gSAAvACigIMCAAQARhlIFMoRTAP&rs=AOn4CLDL2DkJpiucB0Hi52sSSsbx4uK46g", "duration": 108.0, "channel": "אהבת נפש יואל שוורץ", "source": "YouTube", "kind": "video", "formats": [{"label": "MP4 מלא", "value": "best", "format": "video"}, {"label": "MP4 1080p", "value": "1080", "format": "video"}, {"label": "MP4 720p", "value": "720", "format": "video"}, {"label": "MP4 480p", "value": "480", "format": "video"}, {"label": "MP3 שמע", "value": "best", "format": "audio"}], "description": "", "date": ""}, {"title": "תיעוד מרגש וקורע לב: שגב כלפון במפגש ראשון עם משפחתו", "url": "https://www.youtube.com/watch?v=zHQNhfmLznU", "thumb": "https://i.ytimg.com/vi/zHQNhfmLznU/hqdefault.jpg?sqp=-oaymwE2COADEI4CSFXyq4qpAygIARUAAIhCGAFwAcABBvABAfgBzgaAAuADigIMCAAQARhlIFYoRTAP&rs=AOn4CLBJeneZ4zFy-PPWS7zQMvZzzel2Jg", "duration": 52.0, "channel": "ערוץ 7", "source": "YouTube", "kind": "video", "formats": [{"label": "MP4 מלא", "value": "best", "format": "video"}, {"label": "MP4 1080p", "value": "1080", "format": "video"}, {"label": "MP4 720p", "value": "720", "format": "video"}, {"label": "MP4 480p", "value": "480", "format": "video"}, {"label": "MP3 שמע", "value": "best", "format": "audio"}], "description": "", "date": ""}, {"title": "פרופ' קובי מיכאל בראיון לליאת רגב בכאן רשת ב', 6.9.25", "url": "https://www.youtube.com/watch?v=m_Fs3BW3c2g", "thumb": "https://i.ytimg.com/vi/m_Fs3BW3c2g/hqdefault.jpg?sqp=-oaymwE2COADEI4CSFXyq4qpAygIARUAAIhCGAFwAcABBvABAfgB_gSAAuADigIMCAAQARgTIF0ofzAP&rs=AOn4CLDC-w1KNpPs6hs2qXxTKL6Vn7yQMA", "duration": 932.0, "channel": "מכון משגב | Misgav Institute", "source": "YouTube", "kind": "video", "formats": [{"label": "MP4 מלא", "value": "best", "format": "video"}, {"label": "MP4 1080p", "value": "1080", "format": "video"}, {"label": "MP4 720p", "value": "720", "format": "video"}, {"label": "MP4 480p", "value": "480", "format": "video"}, {"label": "MP3 שמע", "value": "best", "format": "audio"}], "description": "", "date": ""}, {"title": "אשר פרדמן בראיון לערוץ 14, 6.12.24", "url": "https://www.youtube.com/watch?v=R32aXKETGgs", "thumb": "https://i.ytimg.com/vi/R32aXKETGgs/hq720.jpg?sqp=-oaymwE2CNAFEJQDSFXyq4qpAygIARUAAIhCGAFwAcABBvABAfgB_gmAAtAFigIMCAAQARgzIFIofzAP&rs=AOn4CLAuOMKRdB4jurGzg-1Hvqt9ShfwbQ", "duration": 247.0, "channel": "מכון משגב | Misgav Institute", "source": "YouTube", "kind": "video", "formats": [{"label": "MP4 מלא", "value": "best", "format": "video"}, {"label": "MP4 1080p", "value": "1080", "format": "video"}, {"label": "MP4 720p", "value": "720", "format": "video"}, {"label": "MP4 480p", "value": "480", "format": "video"}, {"label": "MP3 שמע", "value": "best", "format": "audio"}], "description": "", "date": ""}, {"title": "Freed Israeli hostage Mia Schem in first interview since her release from Hamas captivity in Gaza", "url": "https://www.youtube.com/watch?v=y02xPRX6vCE", "thumb": "https://i.ytimg.com/vi/y02xPRX6vCE/hq720.jpg?sqp=-oaymwEcCNAFEJQDSFXyq4qpAw4IARUAAIhCGAFwAcABBg==&rs=AOn4CLA_3i4CHJ0vMYtEJAX69pR8BXc9Vg", "duration": 1806.0, "channel": "חדשות 13", "source": "YouTube", "kind": "video", "formats": [{"label": "MP4 מלא", "value": "best", "format": "video"}, {"label": "MP4 1080p", "value": "1080", "format": "video"}, {"label": "MP4 720p", "value": "720", "format": "video"}, {"label": "MP4 480p", "value": "480", "format": "video"}, {"label": "MP3 שמע", "value": "best", "format": "audio"}], "description": "", "date": ""}, {"title": "המעגל נסגר: החטוף האחרון רן גואילי ז\"ל הושב לישראל אחרי 843 ימים בעזה", "url": "https://www.youtube.com/watch?v=fvQWuNqVoTc", "thumb": "https://i.ytimg.com/vi/fvQWuNqVoTc/hq720.jpg?sqp=-oaymwEcCNAFEJQDSFXyq4qpAw4IARUAAIhCGAFwAcABBg==&rs=AOn4CLBQDrp0BWUeFPiZa7NPfGYHfi043Q", "duration": 181.0, "channel": "כאן | חדשות - תאגיד השידור הישראלי", "source": "YouTube", "kind": "video", "formats": [{"label": "MP4 מלא", "value": "best", "format": "video"}, {"label": "MP4 1080p", "value": "1080", "format": "video"}, {"label": "MP4 720p", "value": "720", "format": "video"}, {"label": "MP4 480p", "value": "480", "format": "video"}, {"label": "MP3 שמע", "value": "best", "format": "audio"}], "description": "", "date": ""}, {"title": "דודו של החטוף אבינתן אור: \"לא מאמין שחמאס יחזיר את החטופים\" | יומן הצהריים, 13.01.2025", "url": "https://www.youtube.com/watch?v=d1FqSX3z12s", "thumb": "https://i.ytimg.com/vi/d1FqSX3z12s/hq720.jpg?sqp=-oaymwE2CNAFEJQDSFXyq4qpAygIARUAAIhCGAFwAcABBvABAfgB_gmAAtAFigIMCAAQARhlIE0oPjAP&rs=AOn4CLAtOzjpeEruA7UoffQc7daNoaTrow", "duration": 316.0, "channel": "GLZ Radio גלצ", "source": "YouTube", "kind": "video", "formats": [{"label": "MP4 מלא", "value": "best", "format": "video"}, {"label": "MP4 1080p", "value": "1080", "format": "video"}, {"label": "MP4 720p", "value": "720", "format": "video"}, {"label": "MP4 480p", "value": "480", "format": "video"}, {"label": "MP3 שמע", "value": "best", "format": "audio"}], "description": "", "date": ""}, {"title": "ציפי שחרור בראיון טלויזיוני בקונטנטו דה סמריק, בית הוצאה לאור בינלאומי", "url": "https://www.youtube.com/watch?v=K6QVPVOZy8U", "thumb": "https://i.ytimg.com/vi/K6QVPVOZy8U/hq720.jpg?sqp=-oaymwEcCNAFEJQDSFXyq4qpAw4IARUAAIhCGAFwAcABBg==&rs=AOn4CLArq8i3ZGUV5nQDlL0cjRmYgNw5kw", "duration": 254.0, "channel": "Contento Now נתנאל סמריק", "source": "YouTube", "kind": "video", "formats": [{"label": "MP4 מלא", "value": "best", "format": "video"}, {"label": "MP4 1080p", "value": "1080", "format": "video"}, {"label": "MP4 720p", "value": "720", "format": "video"}, {"label": "MP4 480p", "value": "480", "format": "video"}, {"label": "MP3 שמע", "value": "best", "format": "audio"}], "description": "", "date": ""}, {"title": "בכיר באמ\"ן: \"אילו היה לנו מספיק מידע, היינו ממשיכים במבצעי שחרור החטופים\"", "url": "https://www.youtube.com/watch?v=wOoqAywGjBs", "thumb": "https://i.ytimg.com/vi/wOoqAywGjBs/hqdefault.jpg?sqp=-oaymwE2COADEI4CSFXyq4qpAygIARUAAIhCGAFwAcABBvABAfgB1AaAAuADigIMCAAQARgwIFEofzAP&rs=AOn4CLBhZNs_ilLHRuhGAiL-hNmBbFBydQ", "duration": 1031.0, "channel": "Jerusalem Center for Security and Foreign Affairs", "source": "YouTube", "kind": "video", "formats": [{"label": "MP4 מלא", "value": "best", "format": "video"}, {"label": "MP4 1080p", "value": "1080", "format": "video"}, {"label": "MP4 720p", "value": "720", "format": "video"}, {"label": "MP4 480p", "value": "480", "format": "video"}, {"label": "MP3 שמע", "value": "best", "format": "audio"}], "description": "", "date": ""}, {"title": "Rom Breslavsky reveals sexual assaults in captivity: \"They stripped me, tied me up naked\"", "url": "https://www.youtube.com/watch?v=HkXou1PucAk", "thumb": "https://i.ytimg.com/vi/HkXou1PucAk/hq720.jpg?sqp=-oaymwEcCNAFEJQDSFXyq4qpAw4IARUAAIhCGAFwAcABBg==&rs=AOn4CLDIcd9s_fAIy6GJbYpdw4xNO92w-g", "duration": 774.0, "channel": "רשת 13", "source": "YouTube", "kind": "video", "formats": [{"label": "MP4 מלא", "value": "best", "format": "video"}, {"label": "MP4 1080p", "value": "1080", "format": "video"}, {"label": "MP4 720p", "value": "720", "format": "video"}, {"label": "MP4 480p", "value": "480", "format": "video"}, {"label": "MP3 שמע", "value": "best", "format": "audio"}], "description": "", "date": ""}, {"title": "\"הן עשו צמות כי היה אסור להן להתחבק\": סיפורי החטופים שחזרו מהשבי", "url": "https://www.youtube.com/watch?v=_2uXsUrdOSQ", "thumb": "https://i.ytimg.com/vi/_2uXsUrdOSQ/hq720.jpg?sqp=-oaymwEcCNAFEJQDSFXyq4qpAw4IARUAAIhCGAFwAcABBg==&rs=AOn4CLCI64NAODOqDmGQUOKzt0doeQdUPQ", "duration": 227.0, "channel": "כאן | חדשות - תאגיד השידור הישראלי", "source": "YouTube", "kind": "video", "formats": [{"label": "MP4 מלא", "value": "best", "format": "video"}, {"label": "MP4 1080p", "value": "1080", "format": "video"}, {"label": "MP4 720p", "value": "720", "format": "video"}, {"label": "MP4 480p", "value": "480", "format": "video"}, {"label": "MP3 שמע", "value": "best", "format": "audio"}], "description": "", "date": ""}, {"title": "אשתו נרצחה, אלמוג בן ה-3 נותר לבד: סיפורו של אור לוי", "url": "https://www.youtube.com/watch?v=55JvGSWnWeg", "thumb": "https://i.ytimg.com/vi/55JvGSWnWeg/hq720.jpg?sqp=-oaymwEcCNAFEJQDSFXyq4qpAw4IARUAAIhCGAFwAcABBg==&rs=AOn4CLAwA8WABOVAQ5ZLq0X0LlIj0FYhNA", "duration": 326.0, "channel": "כאן | חדשות - תאגיד השידור הישראלי", "source": "YouTube", "kind": "video", "formats": [{"label": "MP4 מלא", "value": "best", "format": "video"}, {"label": "MP4 1080p", "value": "1080", "format": "video"}, {"label": "MP4 720p", "value": "720", "format": "video"}, {"label": "MP4 480p", "value": "480", "format": "video"}, {"label": "MP3 שמע", "value": "best", "format": "audio"}], "description": "", "date": ""}, {"title": "שחרור חטופים - עומר שם טוב עומר ונקרט אליה כהן (צילום: רשתות ערביות)", "url": "https://www.youtube.com/watch?v=FAj_ZE9KxwA", "thumb": "https://i.ytimg.com/vi/FAj_ZE9KxwA/hq720.jpg?sqp=-oaymwE2CNAFEJQDSFXyq4qpAygIARUAAIhCGAFwAcABBvABAfgB_gmAAtAFigIMCAAQARhyIFgoOjAP&rs=AOn4CLBzsCfqJGSmjufvwel6JQcXORBU9g", "duration": 617.0, "channel": "חי פה חדשות חיפה", "source": "YouTube", "kind": "video", "formats": [{"label": "MP4 מלא", "value": "best", "format": "video"}, {"label": "MP4 1080p", "value": "1080", "format": "video"}, {"label": "MP4 720p", "value": "720", "format": "video"}, {"label": "MP4 480p", "value": "480", "format": "video"}, {"label": "MP3 שמע", "value": "best", "format": "audio"}], "description": "", "date": ""}, {"title": "וידאו ראשון מרגעי מפגש השבות עם בני משפחותיהן", "url": "https://www.youtube.com/watch?v=Z_qELjvLED8", "thumb": "https://i.ytimg.com/vi/Z_qELjvLED8/hq720.jpg?sqp=-oaymwE2CNAFEJQDSFXyq4qpAygIARUAAIhCGAFwAcABBvABAfgB_gmAAtAFigIMCAAQARhlIFcoQzAP&rs=AOn4CLAr4oWNOw6zyozaCYcczQPjPGKkIQ", "duration": 140.0, "channel": "IsraeliPM", "source": "YouTube", "kind": "video", "formats": [{"label": "MP4 מלא", "value": "best", "format": "video"}, {"label": "MP4 1080p", "value": "1080", "format": "video"}, {"label": "MP4 720p", "value": "720", "format": "video"}, {"label": "MP4 480p", "value": "480", "format": "video"}, {"label": "MP3 שמע", "value": "best", "format": "audio"}], "description": "", "date": ""}, {"title": "עמוס מלכא. ראיון עם עומר ירדני. רשת 13. 30/1/2025", "url": "https://www.youtube.com/watch?v=E8rGK2u8VEQ", "thumb": "https://i.ytimg.com/vi/E8rGK2u8VEQ/hqdefault.jpg?sqp=-oaymwEcCOADEI4CSFXyq4qpAw4IARUAAIhCGAFwAcABBg==&rs=AOn4CLBFRcGYb9L-KBNhgo5hrOxsoKa6JQ", "duration": 393.0, "channel": "Amos Malka", "source": "YouTube", "kind": "video", "formats": [{"label": "MP4 מלא", "value": "best", "format": "video"}, {"label": "MP4 1080p", "value": "1080", "format": "video"}, {"label": "MP4 720p", "value": "720", "format": "video"}, {"label": "MP4 480p", "value": "480", "format": "video"}, {"label": "MP3 שמע", "value": "best", "format": "audio"}], "description": "", "date": ""}, {"title": "פרופ' קובי מיכאל בראיון לרלוונט, 25.3.24", "url": "https://www.youtube.com/watch?v=trc1QXrLR5A", "thumb": "https://i.ytimg.com/vi/trc1QXrLR5A/hq720.jpg?sqp=-oaymwE2CNAFEJQDSFXyq4qpAygIARUAAIhCGAFwAcABBvABAfgB_gmAAtAFigIMCAAQARgaIBMofzAP&rs=AOn4CLAsT3XvVsx3Rs_gqSydNl46zg2GKQ", "duration": 561.0, "channel": "מכון משגב | Misgav Institute", "source": "YouTube", "kind": "video", "formats": [{"label": "MP4 מלא", "value": "best", "format": "video"}, {"label": "MP4 1080p", "value": "1080", "format": "video"}, {"label": "MP4 720p", "value": "720", "format": "video"}, {"label": "MP4 480p", "value": "480", "format": "video"}, {"label": "MP3 שמע", "value": "best", "format": "audio"}], "description": "", "date": ""}, {"title": "\"ציפינו לקבל יותר - יש ויכוח אם זוהי הפרה מצד חמאס\": רותם קופר על התחושות אחרי השחרור החלקי של חללים", "url": "https://www.youtube.com/watch?v=pOPu8XnTfJI", "thumb": "https://i.ytimg.com/vi/pOPu8XnTfJI/hq720.jpg?sqp=-oaymwEcCNAFEJQDSFXyq4qpAw4IARUAAIhCGAFwAcABBg==&rs=AOn4CLDQmkjaj_QcCvf61EiyfUF3mhZJaA", "duration": 662.0, "channel": "i24NEWS עברית", "source": "YouTube", "kind": "video", "formats": [{"label": "MP4 מלא", "value": "best", "format": "video"}, {"label": "MP4 1080p", "value": "1080", "format": "video"}, {"label": "MP4 720p", "value": "720", "format": "video"}, {"label": "MP4 480p", "value": "480", "format": "video"}, {"label": "MP3 שמע", "value": "best", "format": "audio"}], "description": "", "date": ""}, {"title": "פרופ' קובי מיכאל בראיון לערוץ 14, 30.4.24", "url": "https://www.youtube.com/watch?v=1zTPqM-oPu4", "thumb": "https://i.ytimg.com/vi/1zTPqM-oPu4/hqdefault.jpg?sqp=-oaymwE2COADEI4CSFXyq4qpAygIARUAAIhCGAFwAcABBvABAfgB_gSAAuADigIMCAAQARgyIE8ocjAP&rs=AOn4CLCGOzTCfmp9GU6VJiTCd_1TO4Vruw", "duration": 387.0, "channel": "מכון משגב | Misgav Institute", "source": "YouTube", "kind": "video", "formats": [{"label": "MP4 מלא", "value": "best", "format": "video"}, {"label": "MP4 1080p", "value": "1080", "format": "video"}, {"label": "MP4 720p", "value": "720", "format": "video"}, {"label": "MP4 480p", "value": "480", "format": "video"}, {"label": "MP3 שמע", "value": "best", "format": "audio"}], "description": "", "date": ""}, {"title": "שנתיים בלי אות חיים: התאומים גלי וזיוי שהוחזקו בנפרד בשבי - התאחדו", "url": "https://www.youtube.com/watch?v=Rwa62TQveWg", "thumb": "https://i.ytimg.com/vi/Rwa62TQveWg/hq720.jpg?sqp=-oaymwEcCNAFEJQDSFXyq4qpAw4IARUAAIhCGAFwAcABBg==&rs=AOn4CLC5sKUG92fk1n0IA3LDbFuOfziTKA", "duration": 551.0, "channel": "כאן | חדשות - תאגיד השידור הישראלי", "source": "YouTube", "kind": "video", "formats": [{"label": "MP4 מלא", "value": "best", "format": "video"}, {"label": "MP4 1080p", "value": "1080", "format": "video"}, {"label": "MP4 720p", "value": "720", "format": "video"}, {"label": "MP4 480p", "value": "480", "format": "video"}, {"label": "MP3 שמע", "value": "best", "format": "audio"}], "description": "", "date": ""}, {"title": "אל\"מ במיל' פרופ' גבי סיבוני בראיון לגלי ישראל, 1.5.24", "url": "https://www.youtube.com/watch?v=yKrg8ISpeXM", "thumb": "https://i.ytimg.com/vi/yKrg8ISpeXM/hqdefault.jpg?sqp=-oaymwE2COADEI4CSFXyq4qpAygIARUAAIhCGAFwAcABBvABAfgB_gSAAuADigIMCAAQARgTIF0ofzAP&rs=AOn4CLD6LDhuz7VlGMLEliC6bO-ETXkZrw", "duration": 407.0, "channel": "מכון משגב | Misgav Institute", "source": "YouTube", "kind": "video", "formats": [{"label": "MP4 מלא", "value": "best", "format": "video"}, {"label": "MP4 1080p", "value": "1080", "format": "video"}, {"label": "MP4 720p", "value": "720", "format": "video"}, {"label": "MP4 480p", "value": "480", "format": "video"}, {"label": "MP3 שמע", "value": "best", "format": "audio"}], "description": "", "date": ""}, {"title": "\"ידעתי שאני נכנס לגיהינום\": הלינץ', השבי וההתפכחות מהקונספציה | שיחה מטלטלת עם שורד השבי איתן מור", "url": "https://www.youtube.com/watch?v=HXNuV6Bto3E", "thumb": "https://i.ytimg.com/vi/HXNuV6Bto3E/hq720.jpg?sqp=-oaymwEcCNAFEJQDSFXyq4qpAw4IARUAAIhCGAFwAcABBg==&rs=AOn4CLAvWit_CqgDqeU9wJlDOrS4zMqrgQ", "duration": 635.0, "channel": "פודקאסט על המשמעות - תמיר דורטל", "source": "YouTube", "kind": "video", "formats": [{"label": "MP4 מלא", "value": "best", "format": "video"}, {"label": "MP4 1080p", "value": "1080", "format": "video"}, {"label": "MP4 720p", "value": "720", "format": "video"}, {"label": "MP4 480p", "value": "480", "format": "video"}, {"label": "MP3 שמע", "value": "best", "format": "audio"}], "description": "", "date": ""}, {"title": "\"לא מתעסק ברחמים עצמיים\": אלי שרעבי מוציא ספר על השבי - ומדבר על הכול", "url": "https://www.youtube.com/watch?v=guDw-8MeuiQ", "thumb": "https://i.ytimg.com/vi/guDw-8MeuiQ/hq720.jpg?sqp=-oaymwEcCNAFEJQDSFXyq4qpAw4IARUAAIhCGAFwAcABBg==&rs=AOn4CLDp8y4WRNEw_eg9RRpG4zhzrIM02Q", "duration": 1162.0, "channel": "כאן | חדשות - תאגיד השידור הישראלי", "source": "YouTube", "kind": "video", "formats": [{"label": "MP4 מלא", "value": "best", "format": "video"}, {"label": "MP4 1080p", "value": "1080", "format": "video"}, {"label": "MP4 720p", "value": "720", "format": "video"}, {"label": "MP4 480p", "value": "480", "format": "video"}, {"label": "MP3 שמע", "value": "best", "format": "audio"}], "description": "", "date": ""}, {"title": "עמוס מלכא. ראיון עם נסלי ברדה. חדשות הבוקר ערוץ 12. 23/1/2025", "url": "https://www.youtube.com/watch?v=6Tu0NgN8HNg", "thumb": "https://i.ytimg.com/vi/6Tu0NgN8HNg/hqdefault.jpg?sqp=-oaymwEcCOADEI4CSFXyq4qpAw4IARUAAIhCGAFwAcABBg==&rs=AOn4CLAkWWacTTF_ezwT_qz_nVqwbBFv7g", "duration": 529.0, "channel": "Amos Malka", "source": "YouTube", "kind": "video", "formats": [{"label": "MP4 מלא", "value": "best", "format": "video"}, {"label": "MP4 1080p", "value": "1080", "format": "video"}, {"label": "MP4 720p", "value": "720", "format": "video"}, {"label": "MP4 480p", "value": "480", "format": "video"}, {"label": "MP3 שמע", "value": "best", "format": "audio"}], "description": "", "date": ""}, {"title": "בבוקר שחרור בנה מתן: עינב צנגאוקר תקפה באלימות קצין בצה״ל | החדשות", "url": "https://www.youtube.com/watch?v=H4WY4mG99wI", "thumb": "https://i.ytimg.com/vi/H4WY4mG99wI/hq720.jpg?sqp=-oaymwEcCNAFEJQDSFXyq4qpAw4IARUAAIhCGAFwAcABBg==&rs=AOn4CLAxwgPwwwx8nkC-U-9t_6J09mMKZA", "duration": 68.0, "channel": "C14", "source": "YouTube", "kind": "video", "formats": [{"label": "MP4 מלא", "value": "best", "format": "video"}, {"label": "MP4 1080p", "value": "1080", "format": "video"}, {"label": "MP4 720p", "value": "720", "format": "video"}, {"label": "MP4 480p", "value": "480", "format": "video"}, {"label": "MP3 שמע", "value": "best", "format": "audio"}], "description": "", "date": ""}, {"title": "עמוס מלכא. ראיון עם נסלי ברדה. חדשות הבוקר 12. 12 ספטמבר 2024", "url": "https://www.youtube.com/watch?v=ErdtJm3yYg0", "thumb": "https://i.ytimg.com/vi/ErdtJm3yYg0/hqdefault.jpg?sqp=-oaymwEcCOADEI4CSFXyq4qpAw4IARUAAIhCGAFwAcABBg==&rs=AOn4CLBcFnOKUNE8BTY0DMrVXg90oGxI9A", "duration": 486.0, "channel": "Amos Malka", "source": "YouTube", "kind": "video", "formats": [{"label": "MP4 מלא", "value": "best", "format": "video"}, {"label": "MP4 1080p", "value": "1080", "format": "video"}, {"label": "MP4 720p", "value": "720", "format": "video"}, {"label": "MP4 480p", "value": "480", "format": "video"}, {"label": "MP3 שמע", "value": "best", "format": "audio"}], "description": "", "date": ""}, {"title": "תמונות חדשות של גלעד שליט בשבי חמאס", "url": "https://www.youtube.com/watch?v=g0sVxeGLKrA", "thumb": "https://i.ytimg.com/vi/g0sVxeGLKrA/hq720.jpg?sqp=-oaymwEcCNAFEJQDSFXyq4qpAw4IARUAAIhCGAFwAcABBg==&rs=AOn4CLB6CR1dFaNxzw-Wqv7ST9bJvIOAmA", "duration": 38.0, "channel": "ynet", "source": "YouTube", "kind": "video", "formats": [{"label": "MP4 מלא", "value": "best", "format": "video"}, {"label": "MP4 1080p", "value": "1080", "format": "video"}, {"label": "MP4 720p", "value": "720", "format": "video"}, {"label": "MP4 480p", "value": "480", "format": "video"}, {"label": "MP3 שמע", "value": "best", "format": "audio"}], "description": "", "date": ""}, {"title": "ראיון עם אהרון", "url": "https://www.dailymotion.com/video/x825x14", "thumb": "https://s1.dmcdn.net/v/T39Xu1e0Nu1jYtVkI/x240", "duration": 393, "channel": "tarasa", "description": "", "date": "2021-06-22", "source": "Dailymotion", "kind": "video", "formats": [{"label": "MP4 מלא", "value": "best", "format": "video"}, {"label": "MP4 1080p", "value": "1080", "format": "video"}, {"label": "MP4 720p", "value": "720", "format": "video"}, {"label": "MP4 480p", "value": "480", "format": "video"}, {"label": "MP3 שמע", "value": "best", "format": "audio"}]}, {"title": "ראיון עם אברהם שלונסקי", "url": "https://www.dailymotion.com/video/xh2eyc", "thumb": "https://s2.dmcdn.net/v/1jMaq1ep5q9uAwOBZ/x240", "duration": 903, "channel": "Shaul Reznik", "description": "", "date": "2011-02-16", "source": "Dailymotion", "kind": "video", "formats": [{"label": "MP4 מלא", "value": "best", "format": "video"}, {"label": "MP4 1080p", "value": "1080", "format": "video"}, {"label": "MP4 720p", "value": "720", "format": "video"}, {"label": "MP4 480p", "value": "480", "format": "video"}, {"label": "MP3 שמע", "value": "best", "format": "audio"}]}, {"title": "ראיון עם הנער מפרשת הפדופילים", "url": "https://www.dailymotion.com/video/x84ho3", "thumb": "https://s1.dmcdn.net/v/q3fp1e0Nu0Eq8DU3/x240", "duration": 235, "channel": "deep10101010", "description": "", "date": "2009-01-23", "source": "Dailymotion", "kind": "video", "formats": [{"label": "MP4 מלא", "value": "best", "format": "video"}, {"label": "MP4 1080p", "value": "1080", "format": "video"}, {"label": "MP4 720p", "value": "720", "format": "video"}, {"label": "MP4 480p", "value": "480", "format": "video"}, {"label": "MP3 שמע", "value": "best", "format": "audio"}]}, {"title": "ראיון מדובב עם כריסטיאנו רונאלדו", "url": "https://www.dailymotion.com/video/x2ywx7i", "thumb": "https://s1.dmcdn.net/v/Aj1eU1cnpGdSMRJvZ/x240", "duration": 43, "channel": "Derick Britton", "description": "ראיון מדובב עם כריסטיאנו רונאלדו", "date": "2015-07-22", "source": "Dailymotion", "kind": "video", "formats": [{"label": "MP4 מלא", "value": "best", "format": "video"}, {"label": "MP4 1080p", "value": "1080", "format": "video"}, {"label": "MP4 720p", "value": "720", "format": "video"}, {"label": "MP4 480p", "value": "480", "format": "video"}, {"label": "MP3 שמע", "value": "best", "format": "audio"}]}, {"title": "ראיון אישי ומיוחד עם מירב ישראל", "url": "https://www.dailymotion.com/video/x6t3ekh", "thumb": "https://s1.dmcdn.net/v/OYO611clU5-HF0mGv/x240", "duration": 717, "channel": "Boker Tov", "description": "", "date": "2018-09-04", "source": "Dailymotion", "kind": "video", "formats": [{"label": "MP4 מלא", "value": "best", "format": "video"}, {"label": "MP4 1080p", "value": "1080", "format": "video"}, {"label": "MP4 720p", "value": "720", "format": "video"}, {"label": "MP4 480p", "value": "480", "format": "video"}, {"label": "MP3 שמע", "value": "best", "format": "audio"}]}, {"title": "ראיון עם אליאב יום אחרי חלק 1", "url": "https://www.dailymotion.com/video/x6t0ady", "thumb": "https://s2.dmcdn.net/v/OXqcM1cnsI-F7888t/x240", "duration": 365, "channel": "לןייךחיךלי", "description": "", "date": "2018-09-02", "source": "Dailymotion", "kind": "video", "formats": [{"label": "MP4 מלא", "value": "best", "format": "video"}, {"label": "MP4 1080p", "value": "1080", "format": "video"}, {"label": "MP4 720p", "value": "720", "format": "video"}, {"label": "MP4 480p", "value": "480", "format": "video"}, {"label": "MP3 שמע", "value": "best", "format": "audio"}]}, {"title": "ראיון עם יאיר לפיד בפגוש את העיתונות", "url": "https://www.dailymotion.com/video/x7s3s7d", "thumb": "https://s1.dmcdn.net/v/S2ic91e9amLusMEPA/x240", "duration": 445, "channel": "ZioNLight", "description": "22/02/2020 <br /> <br />ח\"כ יאיר לפיד ב\"פגוש את העיתונות\": \"חסרים לנו 2-3 מנדטים כדי להקים ממשלה עם רוב יהודי\".", "date": "2020-02-22", "source": "Dailymotion", "kind": "video", "formats": [{"label": "MP4 מלא", "value": "best", "format": "video"}, {"label": "MP4 1080p", "value": "1080", "format": "video"}, {"label": "MP4 720p", "value": "720", "format": "video"}, {"label": "MP4 480p", "value": "480", "format": "video"}, {"label": "MP3 שמע", "value": "best", "format": "audio"}]}, {"title": "אישי נשי - ראיון עם עו\"ד כנרת בראשי!", "url": "https://www.dailymotion.com/video/x34awl2", "thumb": "https://s1.dmcdn.net/v/BFZDs1clU5-fmdccZ/x240", "duration": 2586, "channel": "Shauna Pleasant", "description": "אישי נשי - ראיון עם עו\"ד כנרת בראשי!", "date": "2015-09-02", "source": "Dailymotion", "kind": "video", "formats": [{"label": "MP4 מלא", "value": "best", "format": "video"}, {"label": "MP4 1080p", "value": "1080", "format": "video"}, {"label": "MP4 720p", "value": "720", "format": "video"}, {"label": "MP4 480p", "value": "480", "format": "video"}, {"label": "MP3 שמע", "value": "best", "format": "audio"}]}, {"title": "אביב גפן - ראיון עם עינב גלילי - 2008", "url": "https://www.dailymotion.com/video/x2w5bxe", "thumb": "https://s2.dmcdn.net/v/ARJEY1e0Nu1mGelo7/x240", "duration": 533, "channel": "Roadmunching", "description": "אביב גפן - ראיון עם עינב גלילי - 2008", "date": "2015-07-01", "source": "Dailymotion", "kind": "video", "formats": [{"label": "MP4 מלא", "value": "best", "format": "video"}, {"label": "MP4 1080p", "value": "1080", "format": "video"}, {"label": "MP4 720p", "value": "720", "format": "video"}, {"label": "MP4 480p", "value": "480", "format": "video"}, {"label": "MP3 שמע", "value": "best", "format": "audio"}]}, {"title": "ראיון עם קסניה ועמרי באייל גולן קורא לך!", "url": "https://www.dailymotion.com/video/x4lvkp7", "thumb": "https://s1.dmcdn.net/v/Gcp-B1cpHUOyuOeKu/x240", "duration": 614, "channel": "elad Ezra", "description": "", "date": "2016-07-26", "source": "Dailymotion", "kind": "video", "formats": [{"label": "MP4 מלא", "value": "best", "format": "video"}, {"label": "MP4 1080p", "value": "1080", "format": "video"}, {"label": "MP4 720p", "value": "720", "format": "video"}, {"label": "MP4 480p", "value": "480", "format": "video"}, {"label": "MP3 שמע", "value": "best", "format": "audio"}]}, {"title": "ראיון עם קלאודמיר פריירה - וואלה ספורט |2017/18|", "url": "https://www.dailymotion.com/video/x6hv0nw", "thumb": "https://s2.dmcdn.net/v/NQPuS1eo_hs9NWk4-/x240", "duration": 148, "channel": "beitarfc", "description": "", "date": "2018-04-15", "source": "Dailymotion", "kind": "video", "formats": [{"label": "MP4 מלא", "value": "best", "format": "video"}, {"label": "MP4 1080p", "value": "1080", "format": "video"}, {"label": "MP4 720p", "value": "720", "format": "video"}, {"label": "MP4 480p", "value": "480", "format": "video"}, {"label": "MP3 שמע", "value": "best", "format": "audio"}]}, {"title": "ראיון עם ערן שפירא מהועד להצלת עמק ססגון", "url": "https://www.dailymotion.com/video/x2vnrwu", "thumb": "https://s2.dmcdn.net/v/AOBGE1e9T2npaaRa2/x240", "duration": 186, "channel": "Samanuio", "description": "ראיון עם ערן שפירא מהועד להצלת עמק ססגון", "date": "2015-06-27", "source": "Dailymotion", "kind": "video", "formats": [{"label": "MP4 מלא", "value": "best", "format": "video"}, {"label": "MP4 1080p", "value": "1080", "format": "video"}, {"label": "MP4 720p", "value": "720", "format": "video"}, {"label": "MP4 480p", "value": "480", "format": "video"}, {"label": "MP3 שמע", "value": "best", "format": "audio"}]}, {"title": "ראיון צפוף עם דוד זהבי מנכל אורבן נדל\"ן", "url": "https://www.dailymotion.com/video/x5szm67", "thumb": "https://s1.dmcdn.net/v/Kx2h_1e36ZuXwH9hd/x240", "duration": 173, "channel": "אורבן נדל\"ן", "description": "מהו תיקון תמ\"א 38/א? איך מחשבים את הזכויות לבנייה? צפו בדוד זהבי, מנכ\"ל משותף חברת אורבן נדלן, עם כל התשובות והמידע! לפרטים נוספים: <br />http://www.xn--4dbcgg1bqcf3e.co.il/", "date": "2017-07-09", "source": "Dailymotion", "kind": "video", "formats": [{"label": "MP4 מלא", "value": "best", "format": "video"}, {"label": "MP4 1080p", "value": "1080", "format": "video"}, {"label": "MP4 720p", "value": "720", "format": "video"}, {"label": "MP4 480p", "value": "480", "format": "video"}, {"label": "MP3 שמע", "value": "best", "format": "audio"}]}, {"title": "חדשות 2: ראיון עם צבי גולדפינגר על המשכנתא בישראל", "url": "https://www.dailymotion.com/video/x4ih1l3", "thumb": "https://s2.dmcdn.net/v/GH0H71e2CupC9QFPO/x240", "duration": 191, "channel": "צבי גולדפינגר – איש עסקים ונדל\"ן", "description": "בקיץ 2014 ירדה ריבית בנק ישראל לשפל היסטורי דאז, לשיעור של 0.25% – מה שהשפיע מאוד על המשכנתא. בכתבה ששודרה בחדשות 2, דווח כי היקף מחזור המשכנתאות ביולי אותה השנה היה מעל מיליארד ש\"ח, גבוה בהרבה בהשווא", "date": "2016-06-27", "source": "Dailymotion", "kind": "video", "formats": [{"label": "MP4 מלא", "value": "best", "format": "video"}, {"label": "MP4 1080p", "value": "1080", "format": "video"}, {"label": "MP4 720p", "value": "720", "format": "video"}, {"label": "MP4 480p", "value": "480", "format": "video"}, {"label": "MP3 שמע", "value": "best", "format": "audio"}]}, {"title": "ראיון עם ערן לוי במגרש פתוח |27-11-2018|", "url": "https://www.dailymotion.com/video/x6y23c5", "thumb": "https://s1.dmcdn.net/v/P2BTb1eoVBzEjwMan/x240", "duration": 1078, "channel": "beitarfc", "description": "", "date": "2018-11-29", "source": "Dailymotion", "kind": "video", "formats": [{"label": "MP4 מלא", "value": "best", "format": "video"}, {"label": "MP4 1080p", "value": "1080", "format": "video"}, {"label": "MP4 720p", "value": "720", "format": "video"}, {"label": "MP4 480p", "value": "480", "format": "video"}, {"label": "MP3 שמע", "value": "best", "format": "audio"}]}, {"title": "ראיון ראשון עם נרי שהודחה מבית האח הגדול VIP", "url": "https://www.dailymotion.com/video/x72sjcx", "thumb": "https://s2.dmcdn.net/v/PWWy11e8pMYTPHXuc/x240", "duration": 772, "channel": "בורוכוב רז", "description": "ראיון ראשון עם נרי שהודחה מבית האח הגדול VIP", "date": "2019-02-21", "source": "Dailymotion", "kind": "video", "formats": [{"label": "MP4 מלא", "value": "best", "format": "video"}, {"label": "MP4 1080p", "value": "1080", "format": "video"}, {"label": "MP4 720p", "value": "720", "format": "video"}, {"label": "MP4 480p", "value": "480", "format": "video"}, {"label": "MP3 שמע", "value": "best", "format": "audio"}]}, {"title": "ראיון עם אלי אוחנה ברדיו ירושלים |7-12-2018|", "url": "https://www.dailymotion.com/video/x6yjw5t", "thumb": "https://s2.dmcdn.net/v/P5MEH1eoQIh8md9fB/x240", "duration": 1519, "channel": "beitarfc", "description": "", "date": "2018-12-07", "source": "Dailymotion", "kind": "video", "formats": [{"label": "MP4 מלא", "value": "best", "format": "video"}, {"label": "MP4 1080p", "value": "1080", "format": "video"}, {"label": "MP4 720p", "value": "720", "format": "video"}, {"label": "MP4 480p", "value": "480", "format": "video"}, {"label": "MP3 שמע", "value": "best", "format": "audio"}]}, {"title": "ראיון עם ח\"כ ד\"ר מיכאל בן ארי - משט אנטישמי", "url": "https://www.dailymotion.com/video/x2xjy5m", "thumb": "https://s1.dmcdn.net/v/AaJog1clbV09AmrAB/x240", "duration": 297, "channel": "Patchlike", "description": "ראיון עם ח\"כ ד\"ר מיכאל בן ארי - משט אנטישמי", "date": "2015-07-10", "source": "Dailymotion", "kind": "video", "formats": [{"label": "MP4 מלא", "value": "best", "format": "video"}, {"label": "MP4 1080p", "value": "1080", "format": "video"}, {"label": "MP4 720p", "value": "720", "format": "video"}, {"label": "MP4 480p", "value": "480", "format": "video"}, {"label": "MP3 שמע", "value": "best", "format": "audio"}]}, {"title": "היחידה ללימודי חוץ אונו - ראיון עם רו_ח אפי לבקוביץ", "url": "https://www.dailymotion.com/video/xue5d6", "thumb": "https://s2.dmcdn.net/v/32l2g1e1WitKzIvo6/x240", "duration": 399, "channel": "לידר לימודי חוץ", "description": "הקרייה האקדמית אונו - אנו מציעים לכם מגוון קורסים ולימודי תעודה ברמה גבוהה ומחיר אטרקטיבי כגון: לימודי עיצוב גרפי, גרפיקה ממוחשבת, פיתוח מנהלים, הנהלת חשבונות ועוד. הכנסו לאתר שלנו לקבלת מידע נוסף:<br", "date": "2012-10-17", "source": "Dailymotion", "kind": "video", "formats": [{"label": "MP4 מלא", "value": "best", "format": "video"}, {"label": "MP4 1080p", "value": "1080", "format": "video"}, {"label": "MP4 720p", "value": "720", "format": "video"}, {"label": "MP4 480p", "value": "480", "format": "video"}, {"label": "MP3 שמע", "value": "best", "format": "audio"}]}, {"title": "ראיון עם המורה של הישאם מבית האח הגדול VIP", "url": "https://www.dailymotion.com/video/x72sk91", "thumb": "https://s1.dmcdn.net/v/PWXE51e0Nu1FRAoCC/x240", "duration": 561, "channel": "בורוכוב רז", "description": "ראיון עם המורה של הישאם מבית האח הגדול VIP", "date": "2019-02-21", "source": "Dailymotion", "kind": "video", "formats": [{"label": "MP4 מלא", "value": "best", "format": "video"}, {"label": "MP4 1080p", "value": "1080", "format": "video"}, {"label": "MP4 720p", "value": "720", "format": "video"}, {"label": "MP4 480p", "value": "480", "format": "video"}, {"label": "MP3 שמע", "value": "best", "format": "audio"}]}, {"title": "שבוע קולנוע ומוח לילדים: ראיון עם ד\"ר ענבל גושן", "url": "https://www.dailymotion.com/video/x350cb1", "thumb": "https://s2.dmcdn.net/v/BK4zD1e0Nu19lloEu/x240", "duration": 268, "channel": "Z Tech", "description": "שבוע קולנוע ומוח לילדים: ראיון עם ד\"ר ענבל גושן", "date": "2015-09-06", "source": "Dailymotion", "kind": "video", "formats": [{"label": "MP4 מלא", "value": "best", "format": "video"}, {"label": "MP4 1080p", "value": "1080", "format": "video"}, {"label": "MP4 720p", "value": "720", "format": "video"}, {"label": "MP4 480p", "value": "480", "format": "video"}, {"label": "MP3 שמע", "value": "best", "format": "audio"}]}, {"title": "ראיון עם משה חוגג במועדון כדורגל FC |7-2-2019|", "url": "https://www.dailymotion.com/video/x720tc8", "thumb": "https://s1.dmcdn.net/v/PRbA81eobm3D36Q86/x240", "duration": 1929, "channel": "beitarfc", "description": "", "date": "2019-02-07", "source": "Dailymotion", "kind": "video", "formats": [{"label": "MP4 מלא", "value": "best", "format": "video"}, {"label": "MP4 1080p", "value": "1080", "format": "video"}, {"label": "MP4 720p", "value": "720", "format": "video"}, {"label": "MP4 480p", "value": "480", "format": "video"}, {"label": "MP3 שמע", "value": "best", "format": "audio"}]}, {"title": "איך תהפכי יועצת פנג שואי? ראיון עם דר' ירון זפרן", "url": "https://www.dailymotion.com/video/xrj482", "thumb": "https://s1.dmcdn.net/v/2mPSY1e0Nu1KSporN/x240", "duration": 130, "channel": "DrZafran", "description": "כיצד פנג שואי עוזר לנו למשוך לחיינו אהבה, שפע, והצלחה? דר' ירון זפרן, מנהל המכללה ללימודים רוחניים, מלמד כיצד להפוך ליועץ פאנג שוואי ולהביא מזל ואנרגיות חיוביות לביתנו ולביתם של אחרים. 03-5660066 http", "date": "2012-06-14", "source": "Dailymotion", "kind": "video", "formats": [{"label": "MP4 מלא", "value": "best", "format": "video"}, {"label": "MP4 1080p", "value": "1080", "format": "video"}, {"label": "MP4 720p", "value": "720", "format": "video"}, {"label": "MP4 480p", "value": "480", "format": "video"}, {"label": "MP3 שמע", "value": "best", "format": "audio"}]}, {"title": "ראיון עם יו\"ר קדימה, שאול מופז אצל ניסים משעל", "url": "https://www.dailymotion.com/video/x2v4jp1", "thumb": "https://s2.dmcdn.net/v/AKmEr1eovrHc2n0fD/x240", "duration": 366, "channel": "Dabney John", "description": "ראיון עם יו\"ר קדימה, שאול מופז אצל ניסים משעל", "date": "2015-06-23", "source": "Dailymotion", "kind": "video", "formats": [{"label": "MP4 מלא", "value": "best", "format": "video"}, {"label": "MP4 1080p", "value": "1080", "format": "video"}, {"label": "MP4 720p", "value": "720", "format": "video"}, {"label": "MP4 480p", "value": "480", "format": "video"}, {"label": "MP3 שמע", "value": "best", "format": "audio"}]}, {"title": "12 8 10   מדד יומי ערוץ 1   ראיון עם דר ספורטה", "url": "https://www.dailymotion.com/video/x4sasp4", "thumb": "https://s2.dmcdn.net/v/HFzl81clSG0Jsh42I/x240", "duration": 215, "channel": "Alex Jamey", "description": "12 8 10   מדד יומי ערוץ 1   ראיון עם דר ספורטה<br/>", "date": "2016-09-07", "source": "Dailymotion", "kind": "video", "formats": [{"label": "MP4 מלא", "value": "best", "format": "video"}, {"label": "MP4 1080p", "value": "1080", "format": "video"}, {"label": "MP4 720p", "value": "720", "format": "video"}, {"label": "MP4 480p", "value": "480", "format": "video"}, {"label": "MP3 שמע", "value": "best", "format": "audio"}]}, {"title": "ראיון עם ניסים ציוני מנכל פתחון לב במשדר ההתרמה המיוחד", "url": "https://www.dailymotion.com/video/x3k4oah", "thumb": "https://s1.dmcdn.net/v/CqzFv1e177M2S-E1U/x240", "duration": 18, "channel": "ניסים ציוני", "description": "ניסים ציוני מנכ\"ל פתחון לב <br />- פתחון לב הינו ארגון גג הומניטרי ארצי (ע\"ר 580328839) הוקם בשנת 1998 מתוך מטרה לפעול למען שכבות המצוקה במדינת ישראל ללא הבדל מין, דת, גזע, מוצא או לאום. <br />במרכזי ", "date": "2015-12-30", "source": "Dailymotion", "kind": "video", "formats": [{"label": "MP4 מלא", "value": "best", "format": "video"}, {"label": "MP4 1080p", "value": "1080", "format": "video"}, {"label": "MP4 720p", "value": "720", "format": "video"}, {"label": "MP4 480p", "value": "480", "format": "video"}, {"label": "MP3 שמע", "value": "best", "format": "audio"}]}, {"title": "ראיון עם משה חוגג אצל אופירה וברקוביץ' |4-1-2019|", "url": "https://www.dailymotion.com/video/x7069yr", "thumb": "https://s2.dmcdn.net/v/PFlFp1epHvVPGXS8z/x240", "duration": 924, "channel": "beitarfc", "description": "", "date": "2019-01-06", "source": "Dailymotion", "kind": "video", "formats": [{"label": "MP4 מלא", "value": "best", "format": "video"}, {"label": "MP4 1080p", "value": "1080", "format": "video"}, {"label": "MP4 720p", "value": "720", "format": "video"}, {"label": "MP4 480p", "value": "480", "format": "video"}, {"label": "MP3 שמע", "value": "best", "format": "audio"}]}, {"title": "ראיון בערוץ 23 בנושא OCD עם ד\"ר בן-ארוש וגדעון פיין", "url": "https://www.dailymotion.com/video/x4c28lu", "thumb": "https://s1.dmcdn.net/v/FdxGI1clYcaBNx_Hk/x240", "duration": 581, "channel": "Collie Madge", "description": "ראיון בערוץ 23 בנושא OCD עם ד\"ר בן-ארוש וגדעון פיין<br/>", "date": "2016-05-23", "source": "Dailymotion", "kind": "video", "formats": [{"label": "MP4 מלא", "value": "best", "format": "video"}, {"label": "MP4 1080p", "value": "1080", "format": "video"}, {"label": "MP4 720p", "value": "720", "format": "video"}, {"label": "MP4 480p", "value": "480", "format": "video"}, {"label": "MP3 שמע", "value": "best", "format": "audio"}]}, {"title": "ראיון נדיר בטלויזיה עם פריד אל אטרש ועבד אל חלים חאפז", "url": "https://www.dailymotion.com/video/x2hp5lk", "thumb": "https://s2.dmcdn.net/v/8-k6O1eoQP18xzZ9n/x240", "duration": 1824, "channel": "eli28isr", "description": "TV interview with Farid Al Atrash and Abdel Halim Hafez", "date": "2015-02-20", "source": "Dailymotion", "kind": "video", "formats": [{"label": "MP4 מלא", "value": "best", "format": "video"}, {"label": "MP4 1080p", "value": "1080", "format": "video"}, {"label": "MP4 720p", "value": "720", "format": "video"}, {"label": "MP4 480p", "value": "480", "format": "video"}, {"label": "MP3 שמע", "value": "best", "format": "audio"}]}, {"title": "וידאו \"צוות מגזין 42: התנדבות - ראיון עם רן פקר ואיזי כנען", "url": "https://www.dailymotion.com/video/x36616b", "thumb": "https://s2.dmcdn.net/v/BRVrp1e0tdrrHxylH/x240", "duration": 482, "channel": "Celena Estep", "description": "וידאו \"צוות מגזין 42: התנדבות - ראיון עם רן פקר ואיזי כנען", "date": "2015-09-10", "source": "Dailymotion", "kind": "video", "formats": [{"label": "MP4 מלא", "value": "best", "format": "video"}, {"label": "MP4 1080p", "value": "1080", "format": "video"}, {"label": "MP4 720p", "value": "720", "format": "video"}, {"label": "MP4 480p", "value": "480", "format": "video"}, {"label": "MP3 שמע", "value": "best", "format": "audio"}]}, {"title": "ראיון עם עידן רול בתכנית הבוקר של לאון ופאולה בערוץ 2", "url": "https://www.dailymotion.com/video/x3ayeh8", "thumb": "https://s2.dmcdn.net/v/BwBFC1e0QCvaZYjpj/x240", "duration": 433, "channel": "Maayan Maman", "description": "הקלטה ועריכה: מעיין ממן", "date": "2015-10-25", "source": "Dailymotion", "kind": "video", "formats": [{"label": "MP4 מלא", "value": "best", "format": "video"}, {"label": "MP4 1080p", "value": "1080", "format": "video"}, {"label": "MP4 720p", "value": "720", "format": "video"}, {"label": "MP4 480p", "value": "480", "format": "video"}, {"label": "MP3 שמע", "value": "best", "format": "audio"}]}, {"title": "ראיון ביוגרפי בטלויזיה עם עבד אל חלים חאפז   Abdel Halim Hafez", "url": "https://www.dailymotion.com/video/x2hp65a", "thumb": "https://s1.dmcdn.net/v/8-kHU1ep5NthUP-S9/x240", "duration": 3230, "channel": "eli28isr", "description": "Full interview on TV with Abdel Halim Hafez", "date": "2015-02-20", "source": "Dailymotion", "kind": "video", "formats": [{"label": "MP4 מלא", "value": "best", "format": "video"}, {"label": "MP4 1080p", "value": "1080", "format": "video"}, {"label": "MP4 720p", "value": "720", "format": "video"}, {"label": "MP4 480p", "value": "480", "format": "video"}, {"label": "MP3 שמע", "value": "best", "format": "audio"}]}, {"title": "צינור עד הבית - ראיון מיוחד עם רמי ורד מתוך בית האח הגדול", "url": "https://www.dailymotion.com/video/x7yyb9y", "thumb": "https://s1.dmcdn.net/v/SkakM1e9cSBmUhy9K/x240", "duration": 484, "channel": "Ziv", "description": "ערוץ האח הגדול בטלגרם - כל הקטעים <br />https://t.me/BigBrotherILchannel <br /> <br />קבוצת האח הגדול בטלגרם - כל הדיבורים <br />https://t.me/BigBrotherIL", "date": "2021-01-27", "source": "Dailymotion", "kind": "video", "formats": [{"label": "MP4 מלא", "value": "best", "format": "video"}, {"label": "MP4 1080p", "value": "1080", "format": "video"}, {"label": "MP4 720p", "value": "720", "format": "video"}, {"label": "MP4 480p", "value": "480", "format": "video"}, {"label": "MP3 שמע", "value": "best", "format": "audio"}]}, {"title": "ראיון עם הרב אלי בן דהן | Interview avec le Rav Elie Ben- Dahan", "url": "https://www.dailymotion.com/video/x2uiydb", "thumb": "https://s2.dmcdn.net/v/AGwH_1clnyuftdz53/x240", "duration": 350, "channel": "Biomuan", "description": "ראיון עם הרב אלי בן דהן | Interview avec le Rav Elie Ben- Dahan", "date": "2015-06-19", "source": "Dailymotion", "kind": "video", "formats": [{"label": "MP4 מלא", "value": "best", "format": "video"}, {"label": "MP4 1080p", "value": "1080", "format": "video"}, {"label": "MP4 720p", "value": "720", "format": "video"}, {"label": "MP4 480p", "value": "480", "format": "video"}, {"label": "MP3 שמע", "value": "best", "format": "audio"}]}, {"title": "מתוך התוכנית בוקר חם ראיון ההדחה המלא עם ספיר עמר מדה וויס ישראל", "url": "https://www.dailymotion.com/video/x5c8pjx", "thumb": "https://s2.dmcdn.net/v/JFlDT1e9wYsKNgAqQ/x240", "duration": 428, "channel": "שוקי טל ערוץ הוידאו", "description": "סליחה על התקלה בתחילת קטע הווידאו מיד המשך סרטון הווידאו ציפייה נעימה <br />רוצים לעדתכן בכל מה שקורה בתוכנית וסדרות הכי טובות והכי חמות של הטלוויזיה הישראלית כנסו עכשיו לעמוד הרשמי של שוקי טל באתר גו", "date": "2017-02-17", "source": "Dailymotion", "kind": "video", "formats": [{"label": "MP4 מלא", "value": "best", "format": "video"}, {"label": "MP4 1080p", "value": "1080", "format": "video"}, {"label": "MP4 720p", "value": "720", "format": "video"}, {"label": "MP4 480p", "value": "480", "format": "video"}, {"label": "MP3 שמע", "value": "best", "format": "audio"}]}, {"title": "תחקיר ישראל היום על פשעי משרד הרווחה - ראיון עם נעמה לנסקי ומיכל יעקב יצחקי", "url": "https://www.dailymotion.com/video/x51xbis", "thumb": "https://s1.dmcdn.net/v/IDesK1e0WCI4TSK5A/x240", "duration": 377, "channel": "Ori Dori", "description": "\"לפקידי הסעד אין את הכלים המקצועיים להחליט\" <br />הוועדה לזכויות הילד מתכנסת היום בכנסת, בעקבות תחקיר \"ישראל היום\" • \"יש תחושה ברורה של חוסר אונים מוחלט\" <br /> <br />אולפן ישראל היום <br />פורסם ב: 3", "date": "2016-11-14", "source": "Dailymotion", "kind": "video", "formats": [{"label": "MP4 מלא", "value": "best", "format": "video"}, {"label": "MP4 1080p", "value": "1080", "format": "video"}, {"label": "MP4 720p", "value": "720", "format": "video"}, {"label": "MP4 480p", "value": "480", "format": "video"}, {"label": "MP3 שמע", "value": "best", "format": "audio"}]}, {"title": "ראיון אישי עם טובה דוד וצילה רייזר, אדריכליות בתוכנית מעצבים תרבות - תוכנית מס' 49", "url": "https://www.dailymotion.com/video/x2s6jky", "thumb": "https://s1.dmcdn.net/v/A1uoY1e3z-y0dvufc/x240", "duration": 1520, "channel": "טובה וצילה משרד אדריכלים ומעצבי פנים", "description": "ראיון אישי עם טובה דוד וצילה רייזר, אדריכליות בתוכנית מעצבים תרבות - תוכנית מס' 49. להתרשמות ממגוון הפרוייקטים שלנו כנסו ל http://www.r-d-arch.co.il", "date": "2015-05-31", "source": "Dailymotion", "kind": "video", "formats": [{"label": "MP4 מלא", "value": "best", "format": "video"}, {"label": "MP4 1080p", "value": "1080", "format": "video"}, {"label": "MP4 720p", "value": "720", "format": "video"}, {"label": "MP4 480p", "value": "480", "format": "video"}, {"label": "MP3 שמע", "value": "best", "format": "audio"}]}, {"title": "שי חי בתוכנית חי בלילה", "url": "https://www.dailymotion.com/video/x3wvf91", "thumb": "https://s1.dmcdn.net/v/E6chr1epA6NYV1Rja/x240", "duration": 298, "channel": "Ram Ziv", "description": "קטע מהתוכנית חי בלילה <br />ראיון עם המאסטר של שי חי - קיוהדה שינג'ו", "date": "2016-03-10", "source": "Dailymotion", "kind": "video", "formats": [{"label": "MP4 מלא", "value": "best", "format": "video"}, {"label": "MP4 1080p", "value": "1080", "format": "video"}, {"label": "MP4 720p", "value": "720", "format": "video"}, {"label": "MP4 480p", "value": "480", "format": "video"}, {"label": "MP3 שמע", "value": "best", "format": "audio"}]}, {"title": "יום התרמה לכבוד עמותת לתת באילת", "url": "https://www.dailymotion.com/video/x844nvg", "thumb": "https://s2.dmcdn.net/v/TFlNS1fyebbYCuLOH/x240", "duration": 355, "channel": "ErevErevEilat", "description": "ראיון עם ערן קורץ (רדיו קול הים האדום) עם מנכ\"ל עיתון 'ערב ערב ' באילת עו\"ד רותם נועם", "date": "2021-09-13", "source": "Dailymotion", "kind": "video", "formats": [{"label": "MP4 מלא", "value": "best", "format": "video"}, {"label": "MP4 1080p", "value": "1080", "format": "video"}, {"label": "MP4 720p", "value": "720", "format": "video"}, {"label": "MP4 480p", "value": "480", "format": "video"}, {"label": "MP3 שמע", "value": "best", "format": "audio"}]}, {"title": "MBD Interview \"Kulam Ahuvim\"", "url": "https://www.dailymotion.com/video/xak5iz", "thumb": "https://s1.dmcdn.net/v/13gBx1e1l6AmcNbyp/x240", "duration": 1048, "channel": "Editor Shlager Net", "description": "ראיון מיוחד עם מרדכי בן דוד לרגל הוצאת האלבום כולם אהובים<br />שלאגר.נט", "date": "2009-09-21", "source": "Dailymotion", "kind": "video", "formats": [{"label": "MP4 מלא", "value": "best", "format": "video"}, {"label": "MP4 1080p", "value": "1080", "format": "video"}, {"label": "MP4 720p", "value": "720", "format": "video"}, {"label": "MP4 480p", "value": "480", "format": "video"}, {"label": "MP3 שמע", "value": "best", "format": "audio"}]}, {"title": "תשומת לב שנטל - שמלות כלה וערב בעיצוב אישי", "url": "https://www.dailymotion.com/video/x1b1g8o", "thumb": "https://s2.dmcdn.net/v/4jPTu1e0NUO0_jWBu/x240", "duration": 146, "channel": "תשומת לב שנטל", "description": "http://www.tsumatlev.co.il/category/landing-pages <br /> <br />תצוגת אופנה באירוע שבוע האפנה לכלות של וואלה מזל טוב. <br />ראיון עם המעצבת הראשית של הסטודיו - שנטל רומנו.", "date": "2014-02-03", "source": "Dailymotion", "kind": "video", "formats": [{"label": "MP4 מלא", "value": "best", "format": "video"}, {"label": "MP4 1080p", "value": "1080", "format": "video"}, {"label": "MP4 720p", "value": "720", "format": "video"}, {"label": "MP4 480p", "value": "480", "format": "video"}, {"label": "MP3 שמע", "value": "best", "format": "audio"}]}, {"title": "דני חלוץ בראיון לעושים צהרים בגל\"צ 10.4.2011", "url": "https://www.dailymotion.com/video/xikh01", "thumb": "https://s1.dmcdn.net/v/1s-KH1e2f9B6SpDDt/x240", "duration": 468, "channel": "דני חלוץ", "description": "לפניכם ראיון שערכה יעל דן עם הרמטכ\"ל לשעבר דני חלוץ בתוכנית עושים צהרים בגלי צה\"ל בעקבות ההסלמה בדרום. http://www.danihaloutz.co.il", "date": "2011-05-05", "source": "Dailymotion", "kind": "video", "formats": [{"label": "MP4 מלא", "value": "best", "format": "video"}, {"label": "MP4 1080p", "value": "1080", "format": "video"}, {"label": "MP4 720p", "value": "720", "format": "video"}, {"label": "MP4 480p", "value": "480", "format": "video"}, {"label": "MP3 שמע", "value": "best", "format": "audio"}]}, {"title": "טיפול שיניים בהרדמה מלאה /  כללית - וידאו המציג רופא מומחה לטיפולי שיניים ביום אחד.", "url": "https://www.dailymotion.com/video/x2tb28w", "thumb": "https://s1.dmcdn.net/v/A96KW1clXHDX-Qcps/x240", "duration": 179, "channel": "מדארט | השתלת שיניים בהרדמה מלאה", "description": "וידאו הסברתי על מרפאות שיניים מדארט המבצעות טיפולי שיניים בהרדמה מלאה.http://goo.gl/z4hbhO <br />ראיון עם הרופאים המטפלים,הצצה לחדרי הניתוח. <br />הסבר מפורט מדוע ואיך צריך לעבור טיפול שיניים בהרדמה מ", "date": "2015-06-10", "source": "Dailymotion", "kind": "video", "formats": [{"label": "MP4 מלא", "value": "best", "format": "video"}, {"label": "MP4 1080p", "value": "1080", "format": "video"}, {"label": "MP4 720p", "value": "720", "format": "video"}, {"label": "MP4 480p", "value": "480", "format": "video"}, {"label": "MP3 שמע", "value": "best", "format": "audio"}]}, {"title": "האלופה עונה 1 פרק 80", "url": "https://www.dailymotion.com/video/x86a3k9", "thumb": "https://s2.dmcdn.net/v/TTXQ91epE_siHk-VJ/x240", "duration": 2120, "channel": "האלופה", "description": "דוד עצוב לשמוע שעובד שוחרר מהקבוצה. לסיגי קשה עם הבשורה של החתונה של תום ומילי. קייזרמן מבשר לשגיא ומילי שהם מקבלים תכנית חדשה. עובד מספר ליפית שהעיפו אותו מהקבוצה. דובי מזועזע כשדריה מספרת לו על מה ש", "date": "2021-12-14", "source": "Dailymotion", "kind": "video", "formats": [{"label": "MP4 מלא", "value": "best", "format": "video"}, {"label": "MP4 1080p", "value": "1080", "format": "video"}, {"label": "MP4 720p", "value": "720", "format": "video"}, {"label": "MP4 480p", "value": "480", "format": "video"}, {"label": "MP3 שמע", "value": "best", "format": "audio"}]}, {"title": "העולם הלילה: לגליזציה של קנאביס בקולורדו", "url": "https://www.dailymotion.com/video/x19q8va", "thumb": "https://s2.dmcdn.net/v/4a_nc1eoCSZbTBLjS/x240", "duration": 255, "channel": "קנאביס - מגזין עם כיוון", "description": "יעקב אילון הקדיש את החלק הראשון בתכניתו \"העולם הלילה\" לחוקי הלגליזציה החדשים בקולורדו שנכנסו לתוקפם בתחילת השנה. בקטע הוידאו ראיון מיוחד עם בעלת חנות לממכר קנאביס חוקי בקולורדו", "date": "2014-01-15", "source": "Dailymotion", "kind": "video", "formats": [{"label": "MP4 מלא", "value": "best", "format": "video"}, {"label": "MP4 1080p", "value": "1080", "format": "video"}, {"label": "MP4 720p", "value": "720", "format": "video"}, {"label": "MP4 480p", "value": "480", "format": "video"}, {"label": "MP3 שמע", "value": "best", "format": "audio"}]}, {"title": "ראיון אורי שקד אצל רפי קרסו- פסיכותרפיה הוליסטית קצרת מועד", "url": "https://www.dailymotion.com/video/xl4wbh", "thumb": "https://s2.dmcdn.net/v/27R6T1e4UC5N6WEMh/x240", "duration": 506, "channel": "אורי שקד- שרותי כתיבה שיווקית ותוכן", "description": "ראיון של אורי שקד בערוץ 10 עם פרופסור רפי קרסו. הראיון עוסק בטיפולים קצרי מועד באמצעות פסיכותרפיה הוליסטית. טיפולים קצרי מועד ממוקדי מטרה להשגת יעדים ברורים וישימים באמצעות כלים וטכניקות מתקדמות מעולם", "date": "2011-09-16", "source": "Dailymotion", "kind": "video", "formats": [{"label": "MP4 מלא", "value": "best", "format": "video"}, {"label": "MP4 1080p", "value": "1080", "format": "video"}, {"label": "MP4 720p", "value": "720", "format": "video"}, {"label": "MP4 480p", "value": "480", "format": "video"}, {"label": "MP3 שמע", "value": "best", "format": "audio"}]}, {"title": "מוטי נתיב - פלדנקרייז ואומנוית הלחימה", "url": "https://www.dailymotion.com/video/xi29hf", "thumb": "https://s1.dmcdn.net/v/1pkw31e0RX77aTOGJ/x240", "duration": 210, "channel": "ענת שץ", "description": "ראיון שעשיתי עם שיהאן מוטי נתיב איך פלדנקרייז מועיל לעוסקים באומנויות הלחימה ובכלל http://www.bujinkan-israel.co.il/ כדי לקבל טיפים חינמיים מענת שץ בנושא תנועה,  http://now.makor-ha-osher.co.il/?page_", "date": "2011-04-11", "source": "Dailymotion", "kind": "video", "formats": [{"label": "MP4 מלא", "value": "best", "format": "video"}, {"label": "MP4 1080p", "value": "1080", "format": "video"}, {"label": "MP4 720p", "value": "720", "format": "video"}, {"label": "MP4 480p", "value": "480", "format": "video"}, {"label": "MP3 שמע", "value": "best", "format": "audio"}]}, {"title": "ד\"ר מרים גרבר מסבירה על עולם האירידיולוגיה בראיון עם אילון בן יוסף", "url": "https://www.dailymotion.com/video/x4pqk1w", "thumb": "https://s1.dmcdn.net/v/G_Z441e0P1z33esZh/x240", "duration": 464, "channel": "ד\"ר מרים גרבר - אירידיולוגיה וריפוי טבעי", "description": "מתוך התוכנית המרתקת של אילון בן יוסף, ראיון עם ד\"ר מרים גרבר על מגוון שיטות טיפול חדשניות וטבעיות ללא כאבים אשריכולים למנוע מחלות נוראיות. <br />למידע נוסף ופגישת ייעוץ חינם כנסו לאתר <br />http://www", "date": "2017-06-27", "source": "Dailymotion", "kind": "video", "formats": [{"label": "MP4 מלא", "value": "best", "format": "video"}, {"label": "MP4 1080p", "value": "1080", "format": "video"}, {"label": "MP4 720p", "value": "720", "format": "video"}, {"label": "MP4 480p", "value": "480", "format": "video"}, {"label": "MP3 שמע", "value": "best", "format": "audio"}]}, {"title": "קורס  קוד מנצח של ערן שטרן ואלון אולמן  | לילך דרור מגירות", "url": "https://www.dailymotion.com/video/xa1auu", "thumb": "https://s1.dmcdn.net/v/10JSs1e9GbtpHs8Uc/x240", "duration": 334, "channel": "megirot", "description": "ראיון שעשתה לילך דרור ממגירות עם ערן שטרן ואלון אולמן בגמר הסדנא המדהימה שלהם שנקראת \" קוד מנצח\" סדנא שעוזרת לפרוץ לגבולות חדשים. שווה מאוד . כנסו לאתר שלהם  http://www.winnerscode.com וגם בואו לבקר א", "date": "2009-08-01", "source": "Dailymotion", "kind": "video", "formats": [{"label": "MP4 מלא", "value": "best", "format": "video"}, {"label": "MP4 1080p", "value": "1080", "format": "video"}, {"label": "MP4 720p", "value": "720", "format": "video"}, {"label": "MP4 480p", "value": "480", "format": "video"}, {"label": "MP3 שמע", "value": "best", "format": "audio"}]}, {"title": "עורך דין רשלנות רפואית", "url": "https://www.dailymotion.com/video/xr16cn", "thumb": "https://s1.dmcdn.net/v/2jD5d1e0N5BXPTPRT/x240", "duration": 161, "channel": "טל נבו", "description": "עורך דין רשלנות רפואית - ראיון עם עו\"ד ענת מולסון מסבירה על הגשת תביעות רשלנות רפואית ועל משרד עורכי דין רשלנות רפואית נבו מולסון המטפל במקרים קשים של רשלנות רפואית. יצירת קשר:- טלפון 1800200807<br />", "date": "2012-05-28", "source": "Dailymotion", "kind": "video", "formats": [{"label": "MP4 מלא", "value": "best", "format": "video"}, {"label": "MP4 1080p", "value": "1080", "format": "video"}, {"label": "MP4 720p", "value": "720", "format": "video"}, {"label": "MP4 480p", "value": "480", "format": "video"}, {"label": "MP3 שמע", "value": "best", "format": "audio"}]}]}